yeroyan_clustering/__init__.py
yeroyan_clustering/main.py
yeroyan_clustering/utils.py
yeroyan_clustering/data/telco.csv
yeroyan_clustering/data/titanic.csv
yeroyan_clustering/modeling/__init__.py
yeroyan_clustering/modeling/base_models.py
yeroyan_clustering/modeling/kmeans.py
yeroyan_clustering/notebooks/analysis.ipynb
yeroyan_clustering/processing/__init__.py
yeroyan_clustering/processing/dataset_processing.py
yeroyan_clustering/processing/dimensionality_reduction.py
yeroyan_clustering-0.1.3.dist-info/AUTHORS.rst
yeroyan_clustering-0.1.3.dist-info/LICENSE
yeroyan_clustering-0.1.3.dist-info/METADATA
yeroyan_clustering-0.1.3.dist-info/WHEEL
yeroyan_clustering-0.1.3.dist-info/top_level.txt
yeroyan_clustering-0.1.3.dist-info/RECORD
