Metadata-Version: 2.1
Name: yeroyan_clustering
Version: 0.1.3
Summary: Automated Clustering and Anomaly Detection
Home-page: https://github.com/Ara-Yeroyan/yeroyan_clustering
Author: Ara Yeroyan
Author-email: ar23yeroyan@gmail.com
License: Apache Software License 2.0
Keywords: yeroyan_clustering
Classifier: Development Status :: 2 - Pre-Alpha
Classifier: Intended Audience :: Developers
Classifier: License :: OSI Approved :: Apache Software License
Classifier: Natural Language :: English
Classifier: Programming Language :: Python :: 3.10
Classifier: Programming Language :: Python :: 3.11
Requires-Python: >=3.10
License-File: LICENSE
License-File: AUTHORS.rst
